<?xml version="1.0" encoding="UTF-8"?>
<quotes>
    <quote>
        <author>R. Buckminster Fuller</author>
        <content>Either war is obsolete or men are.</content>
    </quote>
    <quote>
        <author>Eleanor Roosevelt</author>
        <content>We have to face the fact that either all of us are going to die together or we are going to learn to live together and if we are to live together we have to talk.</content>
    </quote>
    <quote>
        <author>Issac Asimov</author>
        <content>Violence is the first refuge of the incompetent.</content>
    </quote>
    <quote>
        <author>Herbert Hoover</author>
        <content>Older men declare war. But it's the youth who must fight and die!</content>
    </quote>
    <quote>
        <author>Jeannette Rankin, First Woman Member of Congress</author>
        <content>You can no more win a war than you can win an earthquake.</content>
    </quote>
    <quote>
        <author>General Omar Bradley</author>
        <content>In war there is no prize for the runner-up.</content>
    </quote>
    <quote>
        <author>Winston Churchill</author>
        <content>When you have to kill a man it costs nothing to be polite.</content>
    </quote>
    <quote>
        <author>Albert Einstein</author>
        <content>The pioneers of a warless world are the youth that refuse military service.</content>
    </quote>
    <quote>
        <author>Martin Luther King, Jr.</author>
        <content>Our only hope today lies in our ability to recapture the revolutionary spirit and go into a sometimes hostile world declaring eternal hostility to poverty, racism, and militarism.</content>
    </quote>
    <quote>
        <author>Ernest Hemmingway</author>
        <content>They wrote in the old days that it is sweet and fitting to die for one's country. But in modern war, there is nothing sweet nor fitting in your dying. You will die like a dog for no good reason.</content>
    </quote>
</quotes>

